{
  "urls": [
    {
      "url": "http://new.王二小放牛娃.top",
      "name": "🐄王小二放牛娃🐄"
    },
    {
      "url": "http://new.999888123.xyz",
      "name": "🐄王小二放牛娃🐄"
    },
    {
      "url": "http://new.999888987.xyz",
      "name": "🐄王小二放牛娃🐄"
    },
    {
      "url": "https://9280.kstore.vip/newwex.json",
      "name": "🐄王小二放牛娃🐄"
    },
    {
      "url": "http://tvbox.王二小放牛娃.top",
      "name": "🐄王小二放牛娃🐄"
    },
    {
      "url": "http://tvbox.xn--4kq62z5rby2qupq9ub.top",
      "name": "🐄王小二放牛娃🐄"
    },
    {
      "url": "http://tv.999888987.xyz/",
      "name": "🐄王小二放牛娃🐄"
    },
    {
      "url": "http://tv.999888123.xyz/",
      "name": "🐄王小二放牛娃🐄"
    },
    {
      "url": "https://9280.kstore.vip/wex.json",
      "name": "🐄王小二放牛娃🐄"
    }
  ]
}
